{
  "$schema": "https://static.modelcontextprotocol.io/schemas/2025-12-11/server.schema.json",
  "name": "io.github.romanpert/mcp-aemps",
  "title": "MCP AEMPS — CIMA",
  "description": "MCP server for the Spanish AEMPS CIMA pharmaceutical registry (20,000+ authorised medicines).",
  "websiteUrl": "https://github.com/romanpert/mcp-aemps",
  "repository": {
    "url": "https://github.com/romanpert/mcp-aemps",
    "source": "github"
  },
  "icons": [
    {
      "src": "https://raw.githubusercontent.com/romanpert/mcp-aemps/master/docs/icons/icon-64.png",
      "mimeType": "image/png",
      "sizes": ["64x64"]
    },
    {
      "src": "https://raw.githubusercontent.com/romanpert/mcp-aemps/master/docs/icons/icon-128.png",
      "mimeType": "image/png",
      "sizes": ["128x128"]
    },
    {
      "src": "https://raw.githubusercontent.com/romanpert/mcp-aemps/master/docs/icons/icon-256.png",
      "mimeType": "image/png",
      "sizes": ["256x256"]
    }
  ],
  "version": "0.4.13",
  "packages": [
    {
      "registryType": "pypi",
      "registryBaseUrl": "https://pypi.org",
      "identifier": "mcp-aemps",
      "version": "0.4.13",
      "runtimeHint": "uvx",
      "transport": {
        "type": "streamable-http",
        "url": "http://localhost:{PORT}/mcp"
      },
      "packageArguments": [
        {
          "type": "positional",
          "value": "up"
        }
      ],
      "environmentVariables": [
        {
          "name": "PORT",
          "description": "TCP port for the HTTP server (used in transport URL template)",
          "default": "8765"
        },
        {
          "name": "LOG_LEVEL",
          "description": "Logging level (DEBUG, INFO, WARNING, ERROR)",
          "default": "INFO"
        },
        {
          "name": "REDIS_URL",
          "description": "Optional Redis URL for distributed cache and rate limiting (in-memory used if absent)"
        }
      ]
    }
  ]
}
